stix_shifter_modules/carbonblack/__init__.py
stix_shifter_modules/carbonblack/entry_point.py
stix_shifter_modules/carbonblack/configuration/config.json
stix_shifter_modules/carbonblack/configuration/dialects.json
stix_shifter_modules/carbonblack/configuration/lang_en.json
stix_shifter_modules/carbonblack/stix_translation/__init__.py
stix_shifter_modules/carbonblack/stix_translation/json_to_stix_translator.py
stix_shifter_modules/carbonblack/stix_translation/query_constructor.py
stix_shifter_modules/carbonblack/stix_translation/query_translator.py
stix_shifter_modules/carbonblack/stix_translation/results_translator.py
stix_shifter_modules/carbonblack/stix_translation/json/events_to_stix_map.json
stix_shifter_modules/carbonblack/stix_translation/json/from_stix_map.json
stix_shifter_modules/carbonblack/stix_translation/json/operators.json
stix_shifter_modules/carbonblack/stix_translation/json/to_stix_map.json
stix_shifter_modules/carbonblack/stix_translation/json/stix_2_1/from_stix_map.json
stix_shifter_modules/carbonblack/stix_translation/json/stix_2_1/to_stix_map.json
stix_shifter_modules/carbonblack/stix_translation/json/stix_2_1/to_stix_map_events.json
stix_shifter_modules/carbonblack/stix_transmission/__init__.py
stix_shifter_modules/carbonblack/stix_transmission/api_client.py
stix_shifter_modules/carbonblack/stix_transmission/connector.py
stix_shifter_modules/carbonblack/stix_transmission/event_parser.py
stix_shifter_modules_carbonblack-8.0.2.dist-info/licenses/AUTHORS.md
stix_shifter_modules_carbonblack-8.0.2.dist-info/licenses/LICENSE.md
stix_shifter_modules_carbonblack-8.0.2.dist-info/licenses/NOTICE
stix_shifter_modules_carbonblack-8.0.2.dist-info/METADATA
stix_shifter_modules_carbonblack-8.0.2.dist-info/WHEEL
stix_shifter_modules_carbonblack-8.0.2.dist-info/top_level.txt
stix_shifter_modules_carbonblack-8.0.2.dist-info/RECORD
